local_dir_rag/__init__.py
local_dir_rag/document_loader.py
local_dir_rag/embed.py
local_dir_rag/main.py
local_dir_rag/query_with_rag.py
local_dir_rag/text_processor.py
local_dir_rag/vector_store.py
local_dir_rag-0.4.1.dist-info/METADATA
local_dir_rag-0.4.1.dist-info/WHEEL
local_dir_rag-0.4.1.dist-info/entry_points.txt
local_dir_rag-0.4.1.dist-info/RECORD
