Metadata-Version: 2.3
Name: local-dir-rag
Version: 0.4.1
Summary: RAG from documents in a local directory
Author: Sualeh Fatehi
Author-email: sualeh@hotmail.com
Requires-Python: >=3.13,<4.0
Classifier: Programming Language :: Python :: 3
Classifier: Programming Language :: Python :: 3.13
Provides-Extra: dev
Requires-Dist: black (>=24.2.0,<25.0.0) ; extra == "dev"
Requires-Dist: faiss-cpu (>=1.10.0,<2.0.0)
Requires-Dist: langchain (>=0.3.23,<0.4.0)
Requires-Dist: langchain-community (>=0.3.21,<0.4.0)
Requires-Dist: langchain-openai (>=0.3.12,<0.4.0)
Requires-Dist: pycobertura (>=4.0.0,<5.0.0) ; extra == "dev"
Requires-Dist: pylint (>=3.0.2,<4.0.0) ; extra == "dev"
Requires-Dist: pypdf (>=5.4.0,<6.0.0)
Requires-Dist: pytest (>=8.0.0,<9.0.0) ; extra == "dev"
Requires-Dist: pytest-cov (>=5.0.0,<6.0.0) ; extra == "dev"
Requires-Dist: python-dotenv (>=1.1.0,<2.0.0)
Requires-Dist: sentence-transformers (>=4.0.2,<5.0.0)
